pymotiva/__init__.py
pymotiva-0.1.1.dist-info/DESCRIPTION.rst
pymotiva-0.1.1.dist-info/METADATA
pymotiva-0.1.1.dist-info/RECORD
pymotiva-0.1.1.dist-info/WHEEL
pymotiva-0.1.1.dist-info/metadata.json
pymotiva-0.1.1.dist-info/top_level.txt
pymotiva-0.1.1.dist-info/zip-safe
