Metadata-Version: 2.0
Name: pymotiva
Version: 0.1.1
Summary: Python library for Emotiva XMC-1
Home-page: http://github.com/thecynic/pymotiva
Author: Dima Zavin
Author-email: thecynic@gmail.com
License: MIT
Platform: UNKNOWN
Classifier: Development Status :: 3 - Alpha
Classifier: License :: OSI Approved :: MIT License
Classifier: Operating System :: OS Independent
Classifier: Programming Language :: Python
Classifier: Programming Language :: Python :: 3.4
Classifier: Topic :: Home Automation
Classifier: Topic :: Software Development :: Libraries :: Python Modules
